[
    {
        "client_msg_id": "ba57e797-9b38-408f-90a8-d65e03a54cbe",
        "type": "message",
        "text": "LSPをwebsocketに載せてるのかな? <https:\/\/github.com\/sourcegraph\/sourcegraph-typescript>",
        "user": "UNJ2DANJC",
        "ts": "1584197179.172900",
        "team": "T03C4RC8V",
        "user_team": "T03C4RC8V",
        "source_team": "T03C4RC8V",
        "user_profile": {
            "avatar_hash": "c4b0930af904",
            "image_72": "https:\/\/avatars.slack-edge.com\/2019-09-19\/766087996341_c4b0930af904f66d8057_72.png",
            "first_name": "johejo",
            "real_name": "johejo",
            "display_name": "johejo",
            "team": "T03C4RC8V",
            "name": "mitsuo.heijo",
            "is_restricted": false,
            "is_ultra_restricted": false
        },
        "attachments": [
            {
                "service_name": "GitHub",
                "title": "sourcegraph\/sourcegraph-typescript",
                "title_link": "https:\/\/github.com\/sourcegraph\/sourcegraph-typescript",
                "text": "Provides code intelligence for TypeScript. Contribute to sourcegraph\/sourcegraph-typescript development by creating an account on GitHub.",
                "fallback": "GitHub: sourcegraph\/sourcegraph-typescript",
                "thumb_url": "https:\/\/avatars2.githubusercontent.com\/u\/3979584?s=400&v=4",
                "from_url": "https:\/\/github.com\/sourcegraph\/sourcegraph-typescript",
                "thumb_width": 400,
                "thumb_height": 400,
                "service_icon": "https:\/\/a.slack-edge.com\/80588\/img\/unfurl_icons\/github.png",
                "id": 1,
                "original_url": "https:\/\/github.com\/sourcegraph\/sourcegraph-typescript"
            }
        ],
        "blocks": [
            {
                "type": "rich_text",
                "block_id": "HEivS",
                "elements": [
                    {
                        "type": "rich_text_section",
                        "elements": [
                            {
                                "type": "text",
                                "text": "LSPをwebsocketに載せてるのかな? "
                            },
                            {
                                "type": "link",
                                "url": "https:\/\/github.com\/sourcegraph\/sourcegraph-typescript"
                            }
                        ]
                    }
                ]
            }
        ],
        "thread_ts": "1584197179.172900",
        "reply_count": 1,
        "reply_users_count": 1,
        "latest_reply": "1584231203.174400",
        "reply_users": [
            "UEB17JJJE"
        ],
        "replies": [
            {
                "user": "UEB17JJJE",
                "ts": "1584231203.174400"
            }
        ],
        "subscribed": false
    },
    {
        "type": "message",
        "subtype": "channel_join",
        "ts": "1584201533.174200",
        "user": "U0102N1F8H4",
        "text": "<@U0102N1F8H4> has joined the channel"
    },
    {
        "client_msg_id": "e6bd3641-6526-4520-a941-60e27c2c2b07",
        "type": "message",
        "text": "GDScriptのlspも確かwebsocketでした",
        "user": "UEB17JJJE",
        "ts": "1584231203.174400",
        "team": "T03C4RC8V",
        "user_team": "T03C4RC8V",
        "source_team": "T03C4RC8V",
        "user_profile": {
            "avatar_hash": "g83c988365a0",
            "image_72": "https:\/\/secure.gravatar.com\/avatar\/c83c988365a0fabc4c83cdb600268d59.jpg?s=72&d=https%3A%2F%2Fa.slack-edge.com%2Fdf10d%2Fimg%2Favatars%2Fava_0014-72.png",
            "first_name": "",
            "real_name": "Hirokazu Hata",
            "display_name": "h-michael",
            "team": "T03C4RC8V",
            "name": "h.hata.ai.t",
            "is_restricted": false,
            "is_ultra_restricted": false
        },
        "blocks": [
            {
                "type": "rich_text",
                "block_id": "Au6",
                "elements": [
                    {
                        "type": "rich_text_section",
                        "elements": [
                            {
                                "type": "text",
                                "text": "GDScriptのlspも確かwebsocketでした"
                            }
                        ]
                    }
                ]
            }
        ],
        "thread_ts": "1584197179.172900",
        "parent_user_id": "UNJ2DANJC"
    },
    {
        "client_msg_id": "7bb8d31f-af1d-41a3-b2fd-ce6ad9b9bd02",
        "type": "message",
        "text": "`ご意見募集`\nefm-langserverでwhitelistが `['*']`  的な時でも(vim-lspだけですが)blacklistで弾きたいファイルタイプはいろいろあると思います。\n自分として、以下を初期設定する積りですが、「これは普通やっといたほうがいいだろう」というタイプがあればご意見をいたきたく\n<https:\/\/github.com\/tsuyoshicho\/vim-efm-langserver-settings\/issues\/52#issuecomment-596924456>",
        "user": "UAZ33BKV2",
        "ts": "1584241265.176400",
        "team": "T03C4RC8V",
        "user_team": "T03C4RC8V",
        "source_team": "T03C4RC8V",
        "user_profile": {
            "avatar_hash": "ed16847a152d",
            "image_72": "https:\/\/avatars.slack-edge.com\/2018-05-31\/373472791093_ed16847a152da533e013_72.png",
            "first_name": "",
            "real_name": "Tsuyoshi CHO",
            "display_name": "tsuyoshi_cho",
            "team": "T03C4RC8V",
            "name": "tsuyoshi_cho",
            "is_restricted": false,
            "is_ultra_restricted": false
        },
        "attachments": [
            {
                "service_name": "GitHub",
                "title": "feat: add support true blacklist · Issue #52 · tsuyoshicho\/vim-efm-langserver-settings",
                "title_link": "https:\/\/github.com\/tsuyoshicho\/vim-efm-langserver-settings\/issues\/52#issuecomment-596924456",
                "text": "<https:\/\/github.com\/prabirshrestha\/vim-lsp\/blob\/2de8f4d479229eedcb9bf41a878b94fb7e2662ed\/doc\/vim-lsp.txt#L741-L764> lsp support blacklist",
                "fallback": "GitHub: feat: add support true blacklist · Issue #52 · tsuyoshicho\/vim-efm-langserver-settings",
                "thumb_url": "https:\/\/avatars2.githubusercontent.com\/u\/96727?s=400&v=4",
                "from_url": "https:\/\/github.com\/tsuyoshicho\/vim-efm-langserver-settings\/issues\/52#issuecomment-596924456",
                "thumb_width": 400,
                "thumb_height": 400,
                "service_icon": "https:\/\/a.slack-edge.com\/80588\/img\/unfurl_icons\/github.png",
                "id": 1,
                "original_url": "https:\/\/github.com\/tsuyoshicho\/vim-efm-langserver-settings\/issues\/52#issuecomment-596924456"
            }
        ],
        "blocks": [
            {
                "type": "rich_text",
                "block_id": "VCydC",
                "elements": [
                    {
                        "type": "rich_text_section",
                        "elements": [
                            {
                                "type": "text",
                                "text": "ご意見募集",
                                "style": {
                                    "code": true
                                }
                            },
                            {
                                "type": "text",
                                "text": "\nefm-langserverでwhitelistが "
                            },
                            {
                                "type": "text",
                                "text": "['*']",
                                "style": {
                                    "code": true
                                }
                            },
                            {
                                "type": "text",
                                "text": "  的な時でも(vim-lspだけですが)blacklistで弾きたいファイルタイプはいろいろあると思います。\n自分として、以下を初期設定する積りですが、「これは普通やっといたほうがいいだろう」というタイプがあればご意見をいたきたく\n"
                            },
                            {
                                "type": "link",
                                "url": "https:\/\/github.com\/tsuyoshicho\/vim-efm-langserver-settings\/issues\/52#issuecomment-596924456"
                            }
                        ]
                    }
                ]
            }
        ]
    },
    {
        "client_msg_id": "a372e314-662f-40e1-8ca6-08e68049f70a",
        "type": "message",
        "text": "現在再設計中...",
        "user": "UAZ33BKV2",
        "ts": "1584241694.176800",
        "team": "T03C4RC8V",
        "user_team": "T03C4RC8V",
        "source_team": "T03C4RC8V",
        "user_profile": {
            "avatar_hash": "ed16847a152d",
            "image_72": "https:\/\/avatars.slack-edge.com\/2018-05-31\/373472791093_ed16847a152da533e013_72.png",
            "first_name": "",
            "real_name": "Tsuyoshi CHO",
            "display_name": "tsuyoshi_cho",
            "team": "T03C4RC8V",
            "name": "tsuyoshi_cho",
            "is_restricted": false,
            "is_ultra_restricted": false
        },
        "blocks": [
            {
                "type": "rich_text",
                "block_id": "vmKk",
                "elements": [
                    {
                        "type": "rich_text_section",
                        "elements": [
                            {
                                "type": "text",
                                "text": "現在再設計中..."
                            }
                        ]
                    }
                ]
            }
        ]
    },
    {
        "client_msg_id": "1d8b815c-7dd8-40c7-8c39-1415120a6ecf",
        "type": "message",
        "text": "`qf` も入れるとよさそう？",
        "user": "UBNPMJJGM",
        "ts": "1584248190.176900",
        "team": "T03C4RC8V",
        "user_team": "T03C4RC8V",
        "source_team": "T03C4RC8V",
        "user_profile": {
            "avatar_hash": "gc3ec8434af0",
            "image_72": "https:\/\/secure.gravatar.com\/avatar\/0c3ec8434af0d4cbcbd17bd51bcf1154.jpg?s=72&d=https%3A%2F%2Fa.slack-edge.com%2Fdf10d%2Fimg%2Favatars%2Fava_0007-72.png",
            "first_name": "",
            "real_name": "kg8m",
            "display_name": "",
            "team": "T03C4RC8V",
            "name": "an.ironic.man",
            "is_restricted": false,
            "is_ultra_restricted": false
        },
        "blocks": [
            {
                "type": "rich_text",
                "block_id": "cte",
                "elements": [
                    {
                        "type": "rich_text_section",
                        "elements": [
                            {
                                "type": "text",
                                "text": "qf",
                                "style": {
                                    "code": true
                                }
                            },
                            {
                                "type": "text",
                                "text": " も入れるとよさそう？"
                            }
                        ]
                    }
                ]
            }
        ]
    },
    {
        "client_msg_id": "4650a973-7fad-4382-a503-604052dc2329",
        "type": "message",
        "text": "ありがとうございます。\nbuftypeがノーマルじゃないhelpやqfは発動してないっぽい",
        "user": "UAZ33BKV2",
        "ts": "1584249118.177300",
        "team": "T03C4RC8V",
        "user_team": "T03C4RC8V",
        "source_team": "T03C4RC8V",
        "user_profile": {
            "avatar_hash": "ed16847a152d",
            "image_72": "https:\/\/avatars.slack-edge.com\/2018-05-31\/373472791093_ed16847a152da533e013_72.png",
            "first_name": "",
            "real_name": "Tsuyoshi CHO",
            "display_name": "tsuyoshi_cho",
            "team": "T03C4RC8V",
            "name": "tsuyoshi_cho",
            "is_restricted": false,
            "is_ultra_restricted": false
        },
        "edited": {
            "user": "UAZ33BKV2",
            "ts": "1584249147.000000"
        },
        "blocks": [
            {
                "type": "rich_text",
                "block_id": "spFx",
                "elements": [
                    {
                        "type": "rich_text_section",
                        "elements": [
                            {
                                "type": "text",
                                "text": "ありがとうございます。\nbuftypeがノーマルじゃないhelpやqfは発動してないっぽい"
                            }
                        ]
                    }
                ]
            }
        ],
        "reactions": [
            {
                "name": "naruhodo",
                "users": [
                    "UBNPMJJGM"
                ],
                "count": 1
            }
        ]
    },
    {
        "client_msg_id": "71557292-1b6d-41d7-bfd5-fa535ecaad1a",
        "type": "message",
        "text": "ただ、vim-lspだけでaleやcocがどうしてるかは未調査...",
        "user": "UAZ33BKV2",
        "ts": "1584249135.177700",
        "team": "T03C4RC8V",
        "user_team": "T03C4RC8V",
        "source_team": "T03C4RC8V",
        "user_profile": {
            "avatar_hash": "ed16847a152d",
            "image_72": "https:\/\/avatars.slack-edge.com\/2018-05-31\/373472791093_ed16847a152da533e013_72.png",
            "first_name": "",
            "real_name": "Tsuyoshi CHO",
            "display_name": "tsuyoshi_cho",
            "team": "T03C4RC8V",
            "name": "tsuyoshi_cho",
            "is_restricted": false,
            "is_ultra_restricted": false
        },
        "blocks": [
            {
                "type": "rich_text",
                "block_id": "48\/lq",
                "elements": [
                    {
                        "type": "rich_text_section",
                        "elements": [
                            {
                                "type": "text",
                                "text": "ただ、vim-lspだけでaleやcocがどうしてるかは未調査..."
                            }
                        ]
                    }
                ]
            }
        ]
    },
    {
        "client_msg_id": "9ea985d9-3a60-4f54-a332-d499a6875890",
        "type": "message",
        "text": "`diff, man, fern, defx, capture`\n`gina-status, gina-branch, gina-log, gina-reflog, gina-blame`",
        "user": "U8996GYBF",
        "ts": "1584252794.178500",
        "team": "T03C4RC8V",
        "user_team": "T03C4RC8V",
        "source_team": "T03C4RC8V",
        "user_profile": {
            "avatar_hash": "48b1c10b3cf4",
            "image_72": "https:\/\/avatars.slack-edge.com\/2018-03-09\/327298108645_48b1c10b3cf4092337c5_72.png",
            "first_name": "ycino",
            "real_name": "ycino",
            "display_name": "ycino",
            "team": "T03C4RC8V",
            "name": "yuki.ycino",
            "is_restricted": false,
            "is_ultra_restricted": false
        },
        "blocks": [
            {
                "type": "rich_text",
                "block_id": "Kfrp9",
                "elements": [
                    {
                        "type": "rich_text_section",
                        "elements": [
                            {
                                "type": "text",
                                "text": "diff, man, fern, defx, capture",
                                "style": {
                                    "code": true
                                }
                            },
                            {
                                "type": "text",
                                "text": "\n"
                            },
                            {
                                "type": "text",
                                "text": "gina-status, gina-branch, gina-log, gina-reflog, gina-blame",
                                "style": {
                                    "code": true
                                }
                            }
                        ]
                    }
                ]
            }
        ]
    },
    {
        "client_msg_id": "29314b16-432d-4e0a-a6f0-de7a3b20f0e9",
        "type": "message",
        "text": "やっといた方がいいというか、自分が弾いてる例ですが・・・",
        "user": "U8996GYBF",
        "ts": "1584252840.179400",
        "team": "T03C4RC8V",
        "user_team": "T03C4RC8V",
        "source_team": "T03C4RC8V",
        "user_profile": {
            "avatar_hash": "48b1c10b3cf4",
            "image_72": "https:\/\/avatars.slack-edge.com\/2018-03-09\/327298108645_48b1c10b3cf4092337c5_72.png",
            "first_name": "ycino",
            "real_name": "ycino",
            "display_name": "ycino",
            "team": "T03C4RC8V",
            "name": "yuki.ycino",
            "is_restricted": false,
            "is_ultra_restricted": false
        },
        "blocks": [
            {
                "type": "rich_text",
                "block_id": "Fzh",
                "elements": [
                    {
                        "type": "rich_text_section",
                        "elements": [
                            {
                                "type": "text",
                                "text": "やっといた方がいいというか、自分が弾いてる例ですが・・・"
                            }
                        ]
                    }
                ]
            }
        ]
    },
    {
        "client_msg_id": "e1e02766-f3dc-4b51-9bce-29aa1b904d08",
        "type": "message",
        "text": "ginaのはたしかに必要ですねえ、diffやman...manにlspが作られる可能性は...あんまないか",
        "user": "UAZ33BKV2",
        "ts": "1584252856.179800",
        "team": "T03C4RC8V",
        "user_team": "T03C4RC8V",
        "source_team": "T03C4RC8V",
        "user_profile": {
            "avatar_hash": "ed16847a152d",
            "image_72": "https:\/\/avatars.slack-edge.com\/2018-05-31\/373472791093_ed16847a152da533e013_72.png",
            "first_name": "",
            "real_name": "Tsuyoshi CHO",
            "display_name": "tsuyoshi_cho",
            "team": "T03C4RC8V",
            "name": "tsuyoshi_cho",
            "is_restricted": false,
            "is_ultra_restricted": false
        },
        "blocks": [
            {
                "type": "rich_text",
                "block_id": "Wyxvs",
                "elements": [
                    {
                        "type": "rich_text_section",
                        "elements": [
                            {
                                "type": "text",
                                "text": "ginaのはたしかに必要ですねえ、diffやman...manにlspが作られる可能性は...あんまないか"
                            }
                        ]
                    }
                ]
            }
        ]
    },
    {
        "client_msg_id": "48e9e34f-f5db-49a3-b3d8-eeacebb636f1",
        "type": "message",
        "text": "ありがとうございます。",
        "user": "UAZ33BKV2",
        "ts": "1584252863.180000",
        "team": "T03C4RC8V",
        "user_team": "T03C4RC8V",
        "source_team": "T03C4RC8V",
        "user_profile": {
            "avatar_hash": "ed16847a152d",
            "image_72": "https:\/\/avatars.slack-edge.com\/2018-05-31\/373472791093_ed16847a152da533e013_72.png",
            "first_name": "",
            "real_name": "Tsuyoshi CHO",
            "display_name": "tsuyoshi_cho",
            "team": "T03C4RC8V",
            "name": "tsuyoshi_cho",
            "is_restricted": false,
            "is_ultra_restricted": false
        },
        "blocks": [
            {
                "type": "rich_text",
                "block_id": "SyAe",
                "elements": [
                    {
                        "type": "rich_text_section",
                        "elements": [
                            {
                                "type": "text",
                                "text": "ありがとうございます。"
                            }
                        ]
                    }
                ]
            }
        ]
    },
    {
        "client_msg_id": "d6099bed-2a49-4628-a931-40e9aef59728",
        "type": "message",
        "text": "txt弾いてよさそうな気がするけどどうなんだろう",
        "user": "U8996GYBF",
        "ts": "1584252931.180600",
        "team": "T03C4RC8V",
        "user_team": "T03C4RC8V",
        "source_team": "T03C4RC8V",
        "user_profile": {
            "avatar_hash": "48b1c10b3cf4",
            "image_72": "https:\/\/avatars.slack-edge.com\/2018-03-09\/327298108645_48b1c10b3cf4092337c5_72.png",
            "first_name": "ycino",
            "real_name": "ycino",
            "display_name": "ycino",
            "team": "T03C4RC8V",
            "name": "yuki.ycino",
            "is_restricted": false,
            "is_ultra_restricted": false
        },
        "blocks": [
            {
                "type": "rich_text",
                "block_id": "MdV",
                "elements": [
                    {
                        "type": "rich_text_section",
                        "elements": [
                            {
                                "type": "text",
                                "text": "txt弾いてよさそうな気がするけどどうなんだろう"
                            }
                        ]
                    }
                ]
            }
        ]
    },
    {
        "client_msg_id": "1c3f853f-de87-4c70-bc6e-2d45b24ed12f",
        "type": "message",
        "text": "いま、efm-langserverでtextのlinter動かしてますので、そこはちょっと...",
        "user": "UAZ33BKV2",
        "ts": "1584252957.181300",
        "team": "T03C4RC8V",
        "user_team": "T03C4RC8V",
        "source_team": "T03C4RC8V",
        "user_profile": {
            "avatar_hash": "ed16847a152d",
            "image_72": "https:\/\/avatars.slack-edge.com\/2018-05-31\/373472791093_ed16847a152da533e013_72.png",
            "first_name": "",
            "real_name": "Tsuyoshi CHO",
            "display_name": "tsuyoshi_cho",
            "team": "T03C4RC8V",
            "name": "tsuyoshi_cho",
            "is_restricted": false,
            "is_ultra_restricted": false
        },
        "blocks": [
            {
                "type": "rich_text",
                "block_id": "BV7gl",
                "elements": [
                    {
                        "type": "rich_text_section",
                        "elements": [
                            {
                                "type": "text",
                                "text": "いま、efm-langserverでtextのlinter動かしてますので、そこはちょっと..."
                            }
                        ]
                    }
                ]
            }
        ]
    },
    {
        "client_msg_id": "90ec92ec-aff0-4585-8b59-126dde535291",
        "type": "message",
        "text": "readonly \/ nomodifiable は判断の助けになりそう (バッファが作られた瞬間は設定されてないけど)",
        "user": "U03C71D7H",
        "ts": "1584252980.182300",
        "team": "T03C4RC8V",
        "user_team": "T03C4RC8V",
        "source_team": "T03C4RC8V",
        "user_profile": {
            "avatar_hash": "04a676b32692",
            "image_72": "https:\/\/avatars.slack-edge.com\/2015-01-15\/3417067010_04a676b32692fb2507e1_72.jpg",
            "first_name": "thinca",
            "real_name": "thinca",
            "display_name": "thinca",
            "team": "T03C4RC8V",
            "name": "thinca",
            "is_restricted": false,
            "is_ultra_restricted": false
        },
        "blocks": [
            {
                "type": "rich_text",
                "block_id": "lnhV+",
                "elements": [
                    {
                        "type": "rich_text_section",
                        "elements": [
                            {
                                "type": "text",
                                "text": "readonly \/ nomodifiable は判断の助けになりそう (バッファが作られた瞬間は設定されてないけど)"
                            }
                        ]
                    }
                ]
            }
        ]
    },
    {
        "client_msg_id": "743837a3-ad3f-4861-b6d9-0891183d24ae",
        "type": "message",
        "text": "あ、そうなんですね\ntextにlspやりようないかと感じたので、すみません",
        "user": "U8996GYBF",
        "ts": "1584252990.182600",
        "team": "T03C4RC8V",
        "user_team": "T03C4RC8V",
        "source_team": "T03C4RC8V",
        "user_profile": {
            "avatar_hash": "48b1c10b3cf4",
            "image_72": "https:\/\/avatars.slack-edge.com\/2018-03-09\/327298108645_48b1c10b3cf4092337c5_72.png",
            "first_name": "ycino",
            "real_name": "ycino",
            "display_name": "ycino",
            "team": "T03C4RC8V",
            "name": "yuki.ycino",
            "is_restricted": false,
            "is_ultra_restricted": false
        },
        "blocks": [
            {
                "type": "rich_text",
                "block_id": "1Whfc",
                "elements": [
                    {
                        "type": "rich_text_section",
                        "elements": [
                            {
                                "type": "text",
                                "text": "あ、そうなんですね\ntextにlspやりようないかと感じたので、すみません"
                            }
                        ]
                    }
                ]
            }
        ]
    },
    {
        "client_msg_id": "1fab3654-7f22-465d-9bf7-3449ca822582",
        "type": "message",
        "text": "git 関連ですかね。commit の時とか。",
        "user": "U78A6ESHM",
        "ts": "1584253002.183100",
        "team": "T03C4RC8V",
        "user_team": "T03C4RC8V",
        "source_team": "T03C4RC8V",
        "user_profile": {
            "avatar_hash": "aa245483338d",
            "image_72": "https:\/\/avatars.slack-edge.com\/2019-11-14\/833953864853_aa245483338df08cd3b2_72.png",
            "first_name": "heavenshell",
            "real_name": "heavenshell",
            "display_name": "heavenshell",
            "team": "T03C4RC8V",
            "name": "heavenshell",
            "is_restricted": false,
            "is_ultra_restricted": false
        },
        "blocks": [
            {
                "type": "rich_text",
                "block_id": "KZX9",
                "elements": [
                    {
                        "type": "rich_text_section",
                        "elements": [
                            {
                                "type": "text",
                                "text": "git 関連ですかね。commit の時とか。"
                            }
                        ]
                    }
                ]
            }
        ]
    },
    {
        "client_msg_id": "7327a592-d21d-4357-b329-b7198bb2275b",
        "type": "message",
        "text": "というかmanくらいだと書く人むけのlinterは使えるな...(ボケ)",
        "user": "UAZ33BKV2",
        "ts": "1584253003.183200",
        "team": "T03C4RC8V",
        "user_team": "T03C4RC8V",
        "source_team": "T03C4RC8V",
        "user_profile": {
            "avatar_hash": "ed16847a152d",
            "image_72": "https:\/\/avatars.slack-edge.com\/2018-05-31\/373472791093_ed16847a152da533e013_72.png",
            "first_name": "",
            "real_name": "Tsuyoshi CHO",
            "display_name": "tsuyoshi_cho",
            "team": "T03C4RC8V",
            "name": "tsuyoshi_cho",
            "is_restricted": false,
            "is_ultra_restricted": false
        },
        "blocks": [
            {
                "type": "rich_text",
                "block_id": "MzNQx",
                "elements": [
                    {
                        "type": "rich_text_section",
                        "elements": [
                            {
                                "type": "text",
                                "text": "というかmanくらいだと書く人むけのlinterは使えるな...(ボケ)"
                            }
                        ]
                    }
                ]
            }
        ]
    },
    {
        "client_msg_id": "29486c51-246c-4694-867b-529e43a5ad46",
        "type": "message",
        "text": "lspがreadonlyとかチェックをもうちょっと厳しめにしているか、は気になるところ、でも今回こっちがどうこうはできる範囲ではないですね",
        "user": "UAZ33BKV2",
        "ts": "1584253042.184100",
        "team": "T03C4RC8V",
        "user_team": "T03C4RC8V",
        "source_team": "T03C4RC8V",
        "user_profile": {
            "avatar_hash": "ed16847a152d",
            "image_72": "https:\/\/avatars.slack-edge.com\/2018-05-31\/373472791093_ed16847a152da533e013_72.png",
            "first_name": "",
            "real_name": "Tsuyoshi CHO",
            "display_name": "tsuyoshi_cho",
            "team": "T03C4RC8V",
            "name": "tsuyoshi_cho",
            "is_restricted": false,
            "is_ultra_restricted": false
        },
        "blocks": [
            {
                "type": "rich_text",
                "block_id": "jiH",
                "elements": [
                    {
                        "type": "rich_text_section",
                        "elements": [
                            {
                                "type": "text",
                                "text": "lspがreadonlyとかチェックをもうちょっと厳しめにしているか、は気になるところ、でも今回こっちがどうこうはできる範囲ではないですね"
                            }
                        ]
                    }
                ]
            }
        ]
    },
    {
        "client_msg_id": "e8084fd4-a4b9-4e1e-8045-e308db850a1a",
        "type": "message",
        "text": "man は書く場合は別のフォーマットのはず…",
        "user": "U03C71D7H",
        "ts": "1584253044.184200",
        "team": "T03C4RC8V",
        "user_team": "T03C4RC8V",
        "source_team": "T03C4RC8V",
        "user_profile": {
            "avatar_hash": "04a676b32692",
            "image_72": "https:\/\/avatars.slack-edge.com\/2015-01-15\/3417067010_04a676b32692fb2507e1_72.jpg",
            "first_name": "thinca",
            "real_name": "thinca",
            "display_name": "thinca",
            "team": "T03C4RC8V",
            "name": "thinca",
            "is_restricted": false,
            "is_ultra_restricted": false
        },
        "blocks": [
            {
                "type": "rich_text",
                "block_id": "v+bc",
                "elements": [
                    {
                        "type": "rich_text_section",
                        "elements": [
                            {
                                "type": "text",
                                "text": "man は書く場合は別のフォーマットのはず…"
                            }
                        ]
                    }
                ]
            }
        ]
    },
    {
        "client_msg_id": "ca71540b-49fd-4088-a60b-7b9ea34184fa",
        "type": "message",
        "text": "あー、そうだ変換前提だった",
        "user": "UAZ33BKV2",
        "ts": "1584253057.184500",
        "team": "T03C4RC8V",
        "user_team": "T03C4RC8V",
        "source_team": "T03C4RC8V",
        "user_profile": {
            "avatar_hash": "ed16847a152d",
            "image_72": "https:\/\/avatars.slack-edge.com\/2018-05-31\/373472791093_ed16847a152da533e013_72.png",
            "first_name": "",
            "real_name": "Tsuyoshi CHO",
            "display_name": "tsuyoshi_cho",
            "team": "T03C4RC8V",
            "name": "tsuyoshi_cho",
            "is_restricted": false,
            "is_ultra_restricted": false
        },
        "blocks": [
            {
                "type": "rich_text",
                "block_id": "1qXIt",
                "elements": [
                    {
                        "type": "rich_text_section",
                        "elements": [
                            {
                                "type": "text",
                                "text": "あー、そうだ変換前提だった"
                            }
                        ]
                    }
                ]
            }
        ]
    },
    {
        "client_msg_id": "d4c91a56-8cf4-44c7-a904-f2c9cd3f268e",
        "type": "message",
        "text": "gitcommitとgina-commit両方を弾いてる部分がある、ginaはgina-commit返すんだっけ・・・？",
        "user": "U8996GYBF",
        "ts": "1584253097.185200",
        "team": "T03C4RC8V",
        "user_team": "T03C4RC8V",
        "source_team": "T03C4RC8V",
        "user_profile": {
            "avatar_hash": "48b1c10b3cf4",
            "image_72": "https:\/\/avatars.slack-edge.com\/2018-03-09\/327298108645_48b1c10b3cf4092337c5_72.png",
            "first_name": "ycino",
            "real_name": "ycino",
            "display_name": "ycino",
            "team": "T03C4RC8V",
            "name": "yuki.ycino",
            "is_restricted": false,
            "is_ultra_restricted": false
        },
        "blocks": [
            {
                "type": "rich_text",
                "block_id": "prq",
                "elements": [
                    {
                        "type": "rich_text_section",
                        "elements": [
                            {
                                "type": "text",
                                "text": "gitcommitとgina-commit両方を弾いてる部分がある、ginaはgina-commit返すんだっけ・・・？"
                            }
                        ]
                    }
                ]
            }
        ]
    },
    {
        "client_msg_id": "054b9247-8938-47a9-aaf8-e2be12a02ec9",
        "type": "message",
        "text": "ginaでもcommitはgitcommitだったような気がするんだけど",
        "user": "U8996GYBF",
        "ts": "1584253113.185500",
        "team": "T03C4RC8V",
        "user_team": "T03C4RC8V",
        "source_team": "T03C4RC8V",
        "user_profile": {
            "avatar_hash": "48b1c10b3cf4",
            "image_72": "https:\/\/avatars.slack-edge.com\/2018-03-09\/327298108645_48b1c10b3cf4092337c5_72.png",
            "first_name": "ycino",
            "real_name": "ycino",
            "display_name": "ycino",
            "team": "T03C4RC8V",
            "name": "yuki.ycino",
            "is_restricted": false,
            "is_ultra_restricted": false
        },
        "blocks": [
            {
                "type": "rich_text",
                "block_id": "F=T",
                "elements": [
                    {
                        "type": "rich_text_section",
                        "elements": [
                            {
                                "type": "text",
                                "text": "ginaでもcommitはgitcommitだったような気がするんだけど"
                            }
                        ]
                    }
                ]
            }
        ]
    },
    {
        "client_msg_id": "0cdf44a2-9ae9-4ee9-b66d-3cd9172bc71a",
        "type": "message",
        "text": "<https:\/\/github.com\/lambdalisue\/gina.vim\/blob\/master\/ftplugin\/gina-commit.vim>\nあるっぽいが、別に両方ハンドリングしている可能性がある?",
        "user": "UAZ33BKV2",
        "ts": "1584253164.185900",
        "team": "T03C4RC8V",
        "user_team": "T03C4RC8V",
        "source_team": "T03C4RC8V",
        "user_profile": {
            "avatar_hash": "ed16847a152d",
            "image_72": "https:\/\/avatars.slack-edge.com\/2018-05-31\/373472791093_ed16847a152da533e013_72.png",
            "first_name": "",
            "real_name": "Tsuyoshi CHO",
            "display_name": "tsuyoshi_cho",
            "team": "T03C4RC8V",
            "name": "tsuyoshi_cho",
            "is_restricted": false,
            "is_ultra_restricted": false
        },
        "attachments": [
            {
                "service_name": "GitHub",
                "title": "lambdalisue\/gina.vim",
                "title_link": "https:\/\/github.com\/lambdalisue\/gina.vim\/blob\/master\/ftplugin\/gina-commit.vim",
                "text": ":footprints: Asynchronously control git repositories in Neovim\/Vim 8 - lambdalisue\/gina.vim",
                "fallback": "GitHub: lambdalisue\/gina.vim",
                "thumb_url": "https:\/\/avatars3.githubusercontent.com\/u\/546312?s=400&v=4",
                "from_url": "https:\/\/github.com\/lambdalisue\/gina.vim\/blob\/master\/ftplugin\/gina-commit.vim",
                "thumb_width": 400,
                "thumb_height": 400,
                "service_icon": "https:\/\/a.slack-edge.com\/80588\/img\/unfurl_icons\/github.png",
                "id": 1,
                "original_url": "https:\/\/github.com\/lambdalisue\/gina.vim\/blob\/master\/ftplugin\/gina-commit.vim"
            }
        ],
        "blocks": [
            {
                "type": "rich_text",
                "block_id": "neIPl",
                "elements": [
                    {
                        "type": "rich_text_section",
                        "elements": [
                            {
                                "type": "link",
                                "url": "https:\/\/github.com\/lambdalisue\/gina.vim\/blob\/master\/ftplugin\/gina-commit.vim"
                            },
                            {
                                "type": "text",
                                "text": "\nあるっぽいが、別に両方ハンドリングしている可能性がある?"
                            }
                        ]
                    }
                ]
            }
        ]
    },
    {
        "client_msg_id": "ce40c16c-94e5-49b9-837c-4a0cc1bc8596",
        "type": "message",
        "text": "cmdwinはft=cmdwinでしたっけ",
        "user": "U8996GYBF",
        "ts": "1584253215.186500",
        "team": "T03C4RC8V",
        "user_team": "T03C4RC8V",
        "source_team": "T03C4RC8V",
        "user_profile": {
            "avatar_hash": "48b1c10b3cf4",
            "image_72": "https:\/\/avatars.slack-edge.com\/2018-03-09\/327298108645_48b1c10b3cf4092337c5_72.png",
            "first_name": "ycino",
            "real_name": "ycino",
            "display_name": "ycino",
            "team": "T03C4RC8V",
            "name": "yuki.ycino",
            "is_restricted": false,
            "is_ultra_restricted": false
        },
        "blocks": [
            {
                "type": "rich_text",
                "block_id": "lxW",
                "elements": [
                    {
                        "type": "rich_text_section",
                        "elements": [
                            {
                                "type": "text",
                                "text": "cmdwinはft=cmdwinでしたっけ"
                            }
                        ]
                    }
                ]
            }
        ]
    },
    {
        "client_msg_id": "ceaadab2-3db3-4063-9786-4538dfc761e8",
        "type": "message",
        "text": "gina、ちょっと確認してみます",
        "user": "U8996GYBF",
        "ts": "1584253228.186800",
        "team": "T03C4RC8V",
        "user_team": "T03C4RC8V",
        "source_team": "T03C4RC8V",
        "user_profile": {
            "avatar_hash": "48b1c10b3cf4",
            "image_72": "https:\/\/avatars.slack-edge.com\/2018-03-09\/327298108645_48b1c10b3cf4092337c5_72.png",
            "first_name": "ycino",
            "real_name": "ycino",
            "display_name": "ycino",
            "team": "T03C4RC8V",
            "name": "yuki.ycino",
            "is_restricted": false,
            "is_ultra_restricted": false
        },
        "blocks": [
            {
                "type": "rich_text",
                "block_id": "raC",
                "elements": [
                    {
                        "type": "rich_text_section",
                        "elements": [
                            {
                                "type": "text",
                                "text": "gina、ちょっと確認してみます"
                            }
                        ]
                    }
                ]
            }
        ]
    },
    {
        "client_msg_id": "83cb3681-1747-42eb-bbe7-506ba93fe23f",
        "type": "message",
        "text": "vimですね",
        "user": "U9S4G0LJW",
        "ts": "1584253229.186900",
        "team": "T03C4RC8V",
        "user_team": "T03C4RC8V",
        "source_team": "T03C4RC8V",
        "user_profile": {
            "avatar_hash": "b6fceab653cf",
            "image_72": "https:\/\/avatars.slack-edge.com\/2018-03-19\/331496519296_b6fceab653cf61d7dd8b_72.png",
            "first_name": "kuu",
            "real_name": "kuu",
            "display_name": "kuu",
            "team": "T03C4RC8V",
            "name": "kuu",
            "is_restricted": false,
            "is_ultra_restricted": false
        },
        "blocks": [
            {
                "type": "rich_text",
                "block_id": "iNy",
                "elements": [
                    {
                        "type": "rich_text_section",
                        "elements": [
                            {
                                "type": "text",
                                "text": "vimですね"
                            }
                        ]
                    }
                ]
            }
        ]
    },
    {
        "client_msg_id": "c1051b20-0eeb-4d30-a91b-56515341d95d",
        "type": "message",
        "text": "vimか、そこはftで弾けないですね",
        "user": "U8996GYBF",
        "ts": "1584253245.187300",
        "team": "T03C4RC8V",
        "user_team": "T03C4RC8V",
        "source_team": "T03C4RC8V",
        "user_profile": {
            "avatar_hash": "48b1c10b3cf4",
            "image_72": "https:\/\/avatars.slack-edge.com\/2018-03-09\/327298108645_48b1c10b3cf4092337c5_72.png",
            "first_name": "ycino",
            "real_name": "ycino",
            "display_name": "ycino",
            "team": "T03C4RC8V",
            "name": "yuki.ycino",
            "is_restricted": false,
            "is_ultra_restricted": false
        },
        "blocks": [
            {
                "type": "rich_text",
                "block_id": "T\/b5B",
                "elements": [
                    {
                        "type": "rich_text_section",
                        "elements": [
                            {
                                "type": "text",
                                "text": "vimか、そこはftで弾けないですね"
                            }
                        ]
                    }
                ]
            }
        ]
    },
    {
        "client_msg_id": "42ec55ab-42d1-4159-8017-f169625ffd54",
        "type": "message",
        "text": "`!empty(getcmdwintype())` で弾いた",
        "user": "U9S4G0LJW",
        "ts": "1584253274.188400",
        "team": "T03C4RC8V",
        "user_team": "T03C4RC8V",
        "source_team": "T03C4RC8V",
        "user_profile": {
            "avatar_hash": "b6fceab653cf",
            "image_72": "https:\/\/avatars.slack-edge.com\/2018-03-19\/331496519296_b6fceab653cf61d7dd8b_72.png",
            "first_name": "kuu",
            "real_name": "kuu",
            "display_name": "kuu",
            "team": "T03C4RC8V",
            "name": "kuu",
            "is_restricted": false,
            "is_ultra_restricted": false
        },
        "blocks": [
            {
                "type": "rich_text",
                "block_id": "vuik",
                "elements": [
                    {
                        "type": "rich_text_section",
                        "elements": [
                            {
                                "type": "text",
                                "text": "!empty(getcmdwintype())",
                                "style": {
                                    "code": true
                                }
                            },
                            {
                                "type": "text",
                                "text": " で弾いた"
                            }
                        ]
                    }
                ]
            }
        ],
        "reactions": [
            {
                "name": "tiken",
                "users": [
                    "U8996GYBF"
                ],
                "count": 1
            }
        ]
    },
    {
        "client_msg_id": "9ca1c3f0-6752-4f42-adbe-962f4c2f6f57",
        "type": "message",
        "text": "cmdwinからpopupwin、動くのかな",
        "user": "U8996GYBF",
        "ts": "1584253277.188500",
        "team": "T03C4RC8V",
        "user_team": "T03C4RC8V",
        "source_team": "T03C4RC8V",
        "user_profile": {
            "avatar_hash": "48b1c10b3cf4",
            "image_72": "https:\/\/avatars.slack-edge.com\/2018-03-09\/327298108645_48b1c10b3cf4092337c5_72.png",
            "first_name": "ycino",
            "real_name": "ycino",
            "display_name": "ycino",
            "team": "T03C4RC8V",
            "name": "yuki.ycino",
            "is_restricted": false,
            "is_ultra_restricted": false
        },
        "blocks": [
            {
                "type": "rich_text",
                "block_id": "jbt",
                "elements": [
                    {
                        "type": "rich_text_section",
                        "elements": [
                            {
                                "type": "text",
                                "text": "cmdwinからpopupwin、動くのかな"
                            }
                        ]
                    }
                ]
            }
        ]
    },
    {
        "client_msg_id": "56799ca4-17dd-4acc-85bd-3135e72fe40a",
        "type": "message",
        "text": "`:Gina commit` からだと `gina-commit` ですね\ngitcommitと両方入れた方がよさそう",
        "user": "U8996GYBF",
        "ts": "1584253372.189400",
        "team": "T03C4RC8V",
        "user_team": "T03C4RC8V",
        "source_team": "T03C4RC8V",
        "user_profile": {
            "avatar_hash": "48b1c10b3cf4",
            "image_72": "https:\/\/avatars.slack-edge.com\/2018-03-09\/327298108645_48b1c10b3cf4092337c5_72.png",
            "first_name": "ycino",
            "real_name": "ycino",
            "display_name": "ycino",
            "team": "T03C4RC8V",
            "name": "yuki.ycino",
            "is_restricted": false,
            "is_ultra_restricted": false
        },
        "blocks": [
            {
                "type": "rich_text",
                "block_id": "ZrH",
                "elements": [
                    {
                        "type": "rich_text_section",
                        "elements": [
                            {
                                "type": "text",
                                "text": ":Gina commit",
                                "style": {
                                    "code": true
                                }
                            },
                            {
                                "type": "text",
                                "text": " からだと "
                            },
                            {
                                "type": "text",
                                "text": "gina-commit",
                                "style": {
                                    "code": true
                                }
                            },
                            {
                                "type": "text",
                                "text": " ですね\ngitcommitと両方入れた方がよさそう"
                            }
                        ]
                    }
                ]
            }
        ]
    },
    {
        "client_msg_id": "bcb9fdd4-96f1-4fd4-81b2-650cd851ed45",
        "type": "message",
        "text": "前git関連のプラグインにPR送った時はg*commitでやった（いいのか）",
        "user": "U9S4G0LJW",
        "ts": "1584253404.189800",
        "team": "T03C4RC8V",
        "user_team": "T03C4RC8V",
        "source_team": "T03C4RC8V",
        "user_profile": {
            "avatar_hash": "b6fceab653cf",
            "image_72": "https:\/\/avatars.slack-edge.com\/2018-03-19\/331496519296_b6fceab653cf61d7dd8b_72.png",
            "first_name": "kuu",
            "real_name": "kuu",
            "display_name": "kuu",
            "team": "T03C4RC8V",
            "name": "kuu",
            "is_restricted": false,
            "is_ultra_restricted": false
        },
        "blocks": [
            {
                "type": "rich_text",
                "block_id": "etBpL",
                "elements": [
                    {
                        "type": "rich_text_section",
                        "elements": [
                            {
                                "type": "text",
                                "text": "前git関連のプラグインにPR送った時はg*commitでやった（いいのか）"
                            }
                        ]
                    }
                ]
            }
        ]
    },
    {
        "client_msg_id": "67304af9-9365-4bb4-9923-afd4113d874b",
        "type": "message",
        "text": "予想外の弾きそうではあるけどそれでいいかも？",
        "user": "U8996GYBF",
        "ts": "1584253422.190100",
        "team": "T03C4RC8V",
        "user_team": "T03C4RC8V",
        "source_team": "T03C4RC8V",
        "user_profile": {
            "avatar_hash": "48b1c10b3cf4",
            "image_72": "https:\/\/avatars.slack-edge.com\/2018-03-09\/327298108645_48b1c10b3cf4092337c5_72.png",
            "first_name": "ycino",
            "real_name": "ycino",
            "display_name": "ycino",
            "team": "T03C4RC8V",
            "name": "yuki.ycino",
            "is_restricted": false,
            "is_ultra_restricted": false
        },
        "blocks": [
            {
                "type": "rich_text",
                "block_id": "0M4",
                "elements": [
                    {
                        "type": "rich_text_section",
                        "elements": [
                            {
                                "type": "text",
                                "text": "予想外の弾きそうではあるけどそれでいいかも？"
                            }
                        ]
                    }
                ]
            }
        ]
    },
    {
        "client_msg_id": "b097134c-2e9c-4b7e-ba28-973d968b8eb6",
        "type": "message",
        "text": "ひとまず `gina-*` はやっておいてもよさそう",
        "user": "U8996GYBF",
        "ts": "1584253447.190500",
        "team": "T03C4RC8V",
        "user_team": "T03C4RC8V",
        "source_team": "T03C4RC8V",
        "user_profile": {
            "avatar_hash": "48b1c10b3cf4",
            "image_72": "https:\/\/avatars.slack-edge.com\/2018-03-09\/327298108645_48b1c10b3cf4092337c5_72.png",
            "first_name": "ycino",
            "real_name": "ycino",
            "display_name": "ycino",
            "team": "T03C4RC8V",
            "name": "yuki.ycino",
            "is_restricted": false,
            "is_ultra_restricted": false
        },
        "blocks": [
            {
                "type": "rich_text",
                "block_id": "oXbp",
                "elements": [
                    {
                        "type": "rich_text_section",
                        "elements": [
                            {
                                "type": "text",
                                "text": "ひとまず "
                            },
                            {
                                "type": "text",
                                "text": "gina-*",
                                "style": {
                                    "code": true
                                }
                            },
                            {
                                "type": "text",
                                "text": " はやっておいてもよさそう"
                            }
                        ]
                    }
                ]
            }
        ]
    },
    {
        "client_msg_id": "ffa08eba-d981-41a6-97d2-fc022ecc9b2a",
        "type": "message",
        "text": "プラグインごとに対応するの正直キリがないと言う気持ちはある",
        "user": "U03C71D7H",
        "ts": "1584253485.190900",
        "team": "T03C4RC8V",
        "user_team": "T03C4RC8V",
        "source_team": "T03C4RC8V",
        "user_profile": {
            "avatar_hash": "04a676b32692",
            "image_72": "https:\/\/avatars.slack-edge.com\/2015-01-15\/3417067010_04a676b32692fb2507e1_72.jpg",
            "first_name": "thinca",
            "real_name": "thinca",
            "display_name": "thinca",
            "team": "T03C4RC8V",
            "name": "thinca",
            "is_restricted": false,
            "is_ultra_restricted": false
        },
        "blocks": [
            {
                "type": "rich_text",
                "block_id": "3Om",
                "elements": [
                    {
                        "type": "rich_text_section",
                        "elements": [
                            {
                                "type": "text",
                                "text": "プラグインごとに対応するの正直キリがないと言う気持ちはある"
                            }
                        ]
                    }
                ]
            }
        ],
        "reactions": [
            {
                "name": "sorena",
                "users": [
                    "U9S4G0LJW",
                    "U78A6ESHM",
                    "UBNPMJJGM"
                ],
                "count": 3
            }
        ]
    },
    {
        "client_msg_id": "4b1122c3-8cbc-4753-a32f-5bd818d9a643",
        "type": "message",
        "text": "どこまでやるかではありますよね（Issueに結構プラグインのが入ってたから色々書いてしまった）",
        "user": "U8996GYBF",
        "ts": "1584253527.192400",
        "team": "T03C4RC8V",
        "user_team": "T03C4RC8V",
        "source_team": "T03C4RC8V",
        "user_profile": {
            "avatar_hash": "48b1c10b3cf4",
            "image_72": "https:\/\/avatars.slack-edge.com\/2018-03-09\/327298108645_48b1c10b3cf4092337c5_72.png",
            "first_name": "ycino",
            "real_name": "ycino",
            "display_name": "ycino",
            "team": "T03C4RC8V",
            "name": "yuki.ycino",
            "is_restricted": false,
            "is_ultra_restricted": false
        },
        "blocks": [
            {
                "type": "rich_text",
                "block_id": "7VhAY",
                "elements": [
                    {
                        "type": "rich_text_section",
                        "elements": [
                            {
                                "type": "text",
                                "text": "どこまでやるかではありますよね（Issueに結構プラグインのが入ってたから色々書いてしまった）"
                            }
                        ]
                    }
                ]
            }
        ]
    },
    {
        "client_msg_id": "2985bba5-4557-402c-9491-a0f14a8f6d45",
        "type": "message",
        "text": "さっき言った readonly とかその辺りで何かイイカンジにできないだろうか (雑)",
        "user": "U03C71D7H",
        "ts": "1584253528.192500",
        "team": "T03C4RC8V",
        "user_team": "T03C4RC8V",
        "source_team": "T03C4RC8V",
        "user_profile": {
            "avatar_hash": "04a676b32692",
            "image_72": "https:\/\/avatars.slack-edge.com\/2015-01-15\/3417067010_04a676b32692fb2507e1_72.jpg",
            "first_name": "thinca",
            "real_name": "thinca",
            "display_name": "thinca",
            "team": "T03C4RC8V",
            "name": "thinca",
            "is_restricted": false,
            "is_ultra_restricted": false
        },
        "blocks": [
            {
                "type": "rich_text",
                "block_id": "uX0",
                "elements": [
                    {
                        "type": "rich_text_section",
                        "elements": [
                            {
                                "type": "text",
                                "text": "さっき言った readonly とかその辺りで何かイイカンジにできないだろうか (雑)"
                            }
                        ]
                    }
                ]
            }
        ]
    },
    {
        "client_msg_id": "9deaa3ea-e2e5-4a82-b197-3c0bb40a1de8",
        "type": "message",
        "text": "今回のケースだとgitcommitだけ弾いて後はユーザーが指定してねがいい感じ",
        "user": "U9S4G0LJW",
        "ts": "1584253538.192900",
        "team": "T03C4RC8V",
        "user_team": "T03C4RC8V",
        "source_team": "T03C4RC8V",
        "user_profile": {
            "avatar_hash": "b6fceab653cf",
            "image_72": "https:\/\/avatars.slack-edge.com\/2018-03-19\/331496519296_b6fceab653cf61d7dd8b_72.png",
            "first_name": "kuu",
            "real_name": "kuu",
            "display_name": "kuu",
            "team": "T03C4RC8V",
            "name": "kuu",
            "is_restricted": false,
            "is_ultra_restricted": false
        },
        "blocks": [
            {
                "type": "rich_text",
                "block_id": "So3m",
                "elements": [
                    {
                        "type": "rich_text_section",
                        "elements": [
                            {
                                "type": "text",
                                "text": "今回のケースだとgitcommitだけ弾いて後はユーザーが指定してねがいい感じ"
                            }
                        ]
                    }
                ]
            }
        ]
    },
    {
        "client_msg_id": "e35aa872-da89-45d9-a51b-ca5b705db5dc",
        "type": "message",
        "text": "gina であっても commit はさすがに readonly じゃなさそうだな…",
        "user": "U03C71D7H",
        "ts": "1584253589.193600",
        "team": "T03C4RC8V",
        "user_team": "T03C4RC8V",
        "source_team": "T03C4RC8V",
        "user_profile": {
            "avatar_hash": "04a676b32692",
            "image_72": "https:\/\/avatars.slack-edge.com\/2015-01-15\/3417067010_04a676b32692fb2507e1_72.jpg",
            "first_name": "thinca",
            "real_name": "thinca",
            "display_name": "thinca",
            "team": "T03C4RC8V",
            "name": "thinca",
            "is_restricted": false,
            "is_ultra_restricted": false
        },
        "blocks": [
            {
                "type": "rich_text",
                "block_id": "DHR",
                "elements": [
                    {
                        "type": "rich_text_section",
                        "elements": [
                            {
                                "type": "text",
                                "text": "gina であっても commit はさすがに readonly じゃなさそうだな…"
                            }
                        ]
                    }
                ]
            }
        ]
    },
    {
        "client_msg_id": "07c91f06-a73e-4c10-83ba-48fd5e362070",
        "type": "message",
        "text": "むしろreadonlyだと逆に困る",
        "user": "U9S4G0LJW",
        "ts": "1584253613.193900",
        "team": "T03C4RC8V",
        "user_team": "T03C4RC8V",
        "source_team": "T03C4RC8V",
        "user_profile": {
            "avatar_hash": "b6fceab653cf",
            "image_72": "https:\/\/avatars.slack-edge.com\/2018-03-19\/331496519296_b6fceab653cf61d7dd8b_72.png",
            "first_name": "kuu",
            "real_name": "kuu",
            "display_name": "kuu",
            "team": "T03C4RC8V",
            "name": "kuu",
            "is_restricted": false,
            "is_ultra_restricted": false
        },
        "blocks": [
            {
                "type": "rich_text",
                "block_id": "4Yi",
                "elements": [
                    {
                        "type": "rich_text_section",
                        "elements": [
                            {
                                "type": "text",
                                "text": "むしろreadonlyだと逆に困る"
                            }
                        ]
                    }
                ]
            }
        ],
        "reactions": [
            {
                "name": "sorena",
                "users": [
                    "U03C71D7H"
                ],
                "count": 1
            }
        ]
    },
    {
        "client_msg_id": "e4327a32-e11c-4e83-abd8-b5e1a765a27e",
        "type": "message",
        "text": "lspの機能にのっかるので、そうしようもないのです....\nただ、ある程度はデフォルトちゃんとそろえるのが、このプラグインとしては労力のかけどころなのでがんばります",
        "user": "UAZ33BKV2",
        "ts": "1584253657.195200",
        "team": "T03C4RC8V",
        "user_team": "T03C4RC8V",
        "source_team": "T03C4RC8V",
        "user_profile": {
            "avatar_hash": "ed16847a152d",
            "image_72": "https:\/\/avatars.slack-edge.com\/2018-05-31\/373472791093_ed16847a152da533e013_72.png",
            "first_name": "",
            "real_name": "Tsuyoshi CHO",
            "display_name": "tsuyoshi_cho",
            "team": "T03C4RC8V",
            "name": "tsuyoshi_cho",
            "is_restricted": false,
            "is_ultra_restricted": false
        },
        "blocks": [
            {
                "type": "rich_text",
                "block_id": "eGGQ=",
                "elements": [
                    {
                        "type": "rich_text_section",
                        "elements": [
                            {
                                "type": "text",
                                "text": "lspの機能にのっかるので、そうしようもないのです....\nただ、ある程度はデフォルトちゃんとそろえるのが、このプラグインとしては労力のかけどころなのでがんばります"
                            }
                        ]
                    }
                ]
            }
        ]
    },
    {
        "client_msg_id": "4ed56d4a-6f82-4c44-8393-9c3031405000",
        "type": "message",
        "text": "独自ではないのか。単に設定を提供するだけだからか",
        "user": "U03C71D7H",
        "ts": "1584253686.195900",
        "team": "T03C4RC8V",
        "user_team": "T03C4RC8V",
        "source_team": "T03C4RC8V",
        "user_profile": {
            "avatar_hash": "04a676b32692",
            "image_72": "https:\/\/avatars.slack-edge.com\/2015-01-15\/3417067010_04a676b32692fb2507e1_72.jpg",
            "first_name": "thinca",
            "real_name": "thinca",
            "display_name": "thinca",
            "team": "T03C4RC8V",
            "name": "thinca",
            "is_restricted": false,
            "is_ultra_restricted": false
        },
        "blocks": [
            {
                "type": "rich_text",
                "block_id": "HQr",
                "elements": [
                    {
                        "type": "rich_text_section",
                        "elements": [
                            {
                                "type": "text",
                                "text": "独自ではないのか。単に設定を提供するだけだからか"
                            }
                        ]
                    }
                ]
            }
        ]
    },
    {
        "client_msg_id": "2294faaf-b589-45fb-9c7e-854d8911d4ff",
        "type": "message",
        "text": "vim-lsp 側に PR 出せば解決",
        "user": "U03C71D7H",
        "ts": "1584253696.196300",
        "team": "T03C4RC8V",
        "user_team": "T03C4RC8V",
        "source_team": "T03C4RC8V",
        "user_profile": {
            "avatar_hash": "04a676b32692",
            "image_72": "https:\/\/avatars.slack-edge.com\/2015-01-15\/3417067010_04a676b32692fb2507e1_72.jpg",
            "first_name": "thinca",
            "real_name": "thinca",
            "display_name": "thinca",
            "team": "T03C4RC8V",
            "name": "thinca",
            "is_restricted": false,
            "is_ultra_restricted": false
        },
        "blocks": [
            {
                "type": "rich_text",
                "block_id": "EGcqZ",
                "elements": [
                    {
                        "type": "rich_text_section",
                        "elements": [
                            {
                                "type": "text",
                                "text": "vim-lsp 側に PR 出せば解決"
                            }
                        ]
                    }
                ]
            }
        ]
    },
    {
        "client_msg_id": "0cfe0a5c-98a1-45e4-bb3c-4b33221ca1f4",
        "type": "message",
        "text": "後はバッファ名とかか…",
        "user": "U03C71D7H",
        "ts": "1584253727.196600",
        "team": "T03C4RC8V",
        "user_team": "T03C4RC8V",
        "source_team": "T03C4RC8V",
        "user_profile": {
            "avatar_hash": "04a676b32692",
            "image_72": "https:\/\/avatars.slack-edge.com\/2015-01-15\/3417067010_04a676b32692fb2507e1_72.jpg",
            "first_name": "thinca",
            "real_name": "thinca",
            "display_name": "thinca",
            "team": "T03C4RC8V",
            "name": "thinca",
            "is_restricted": false,
            "is_ultra_restricted": false
        },
        "blocks": [
            {
                "type": "rich_text",
                "block_id": "O\/rs",
                "elements": [
                    {
                        "type": "rich_text_section",
                        "elements": [
                            {
                                "type": "text",
                                "text": "後はバッファ名とかか…"
                            }
                        ]
                    }
                ]
            }
        ]
    },
    {
        "client_msg_id": "19cde4f7-674d-4633-af14-dffdfe054707",
        "type": "message",
        "text": "qfreplaceは多分editableかつ弾きたい対象ですかね？",
        "user": "U8996GYBF",
        "ts": "1584253823.197200",
        "team": "T03C4RC8V",
        "user_team": "T03C4RC8V",
        "source_team": "T03C4RC8V",
        "user_profile": {
            "avatar_hash": "48b1c10b3cf4",
            "image_72": "https:\/\/avatars.slack-edge.com\/2018-03-09\/327298108645_48b1c10b3cf4092337c5_72.png",
            "first_name": "ycino",
            "real_name": "ycino",
            "display_name": "ycino",
            "team": "T03C4RC8V",
            "name": "yuki.ycino",
            "is_restricted": false,
            "is_ultra_restricted": false
        },
        "blocks": [
            {
                "type": "rich_text",
                "block_id": "Kot5n",
                "elements": [
                    {
                        "type": "rich_text_section",
                        "elements": [
                            {
                                "type": "text",
                                "text": "qfreplaceは多分editableかつ弾きたい対象ですかね？"
                            }
                        ]
                    }
                ]
            }
        ]
    },
    {
        "client_msg_id": "02117f4b-7d4c-44cb-b01d-f9b9d0c58f4e",
        "type": "message",
        "text": "あー、たしかにqfreplaceもそうですねえ",
        "user": "UAZ33BKV2",
        "ts": "1584253838.197500",
        "team": "T03C4RC8V",
        "user_team": "T03C4RC8V",
        "source_team": "T03C4RC8V",
        "user_profile": {
            "avatar_hash": "ed16847a152d",
            "image_72": "https:\/\/avatars.slack-edge.com\/2018-05-31\/373472791093_ed16847a152da533e013_72.png",
            "first_name": "",
            "real_name": "Tsuyoshi CHO",
            "display_name": "tsuyoshi_cho",
            "team": "T03C4RC8V",
            "name": "tsuyoshi_cho",
            "is_restricted": false,
            "is_ultra_restricted": false
        },
        "blocks": [
            {
                "type": "rich_text",
                "block_id": "QNlc",
                "elements": [
                    {
                        "type": "rich_text_section",
                        "elements": [
                            {
                                "type": "text",
                                "text": "あー、たしかにqfreplaceもそうですねえ"
                            }
                        ]
                    }
                ]
            }
        ]
    },
    {
        "client_msg_id": "60099792-0a67-4b89-b683-3be66cf57ab1",
        "type": "message",
        "text": "作り直さないと…",
        "user": "U03C71D7H",
        "ts": "1584253968.197700",
        "team": "T03C4RC8V",
        "user_team": "T03C4RC8V",
        "source_team": "T03C4RC8V",
        "user_profile": {
            "avatar_hash": "04a676b32692",
            "image_72": "https:\/\/avatars.slack-edge.com\/2015-01-15\/3417067010_04a676b32692fb2507e1_72.jpg",
            "first_name": "thinca",
            "real_name": "thinca",
            "display_name": "thinca",
            "team": "T03C4RC8V",
            "name": "thinca",
            "is_restricted": false,
            "is_ultra_restricted": false
        },
        "blocks": [
            {
                "type": "rich_text",
                "block_id": "m6Hv",
                "elements": [
                    {
                        "type": "rich_text_section",
                        "elements": [
                            {
                                "type": "text",
                                "text": "作り直さないと…"
                            }
                        ]
                    }
                ]
            }
        ]
    },
    {
        "client_msg_id": "90e0219d-d047-461a-9179-cade834a0891",
        "type": "message",
        "text": "弾きたいバッファかどうかをもうちょい柔軟に指定できるように vim-lsp 側を改善するのが先な気がする",
        "user": "U03C71D7H",
        "ts": "1584254088.198400",
        "team": "T03C4RC8V",
        "user_team": "T03C4RC8V",
        "source_team": "T03C4RC8V",
        "user_profile": {
            "avatar_hash": "04a676b32692",
            "image_72": "https:\/\/avatars.slack-edge.com\/2015-01-15\/3417067010_04a676b32692fb2507e1_72.jpg",
            "first_name": "thinca",
            "real_name": "thinca",
            "display_name": "thinca",
            "team": "T03C4RC8V",
            "name": "thinca",
            "is_restricted": false,
            "is_ultra_restricted": false
        },
        "blocks": [
            {
                "type": "rich_text",
                "block_id": "lsCt",
                "elements": [
                    {
                        "type": "rich_text_section",
                        "elements": [
                            {
                                "type": "text",
                                "text": "弾きたいバッファかどうかをもうちょい柔軟に指定できるように vim-lsp 側を改善するのが先な気がする"
                            }
                        ]
                    }
                ]
            }
        ]
    },
    {
        "client_msg_id": "76d916bb-76ab-4528-8165-9bbb06a52352",
        "type": "message",
        "text": "buftype=acwrite 以外で buftype 設定されてたら弾くとかでもいい気がする",
        "user": "U0M7GCBPD",
        "ts": "1584254110.199200",
        "team": "T03C4RC8V",
        "user_team": "T03C4RC8V",
        "source_team": "T03C4RC8V",
        "user_profile": {
            "avatar_hash": "gfdf83c448b8",
            "image_72": "https:\/\/secure.gravatar.com\/avatar\/5fdf83c448b8503add52517c7de0e3cc.jpg?s=72&d=https%3A%2F%2Fa.slack-edge.com%2Fdf10d%2Fimg%2Favatars%2Fava_0026-72.png",
            "first_name": "",
            "real_name": "tyru",
            "display_name": "",
            "team": "T03C4RC8V",
            "name": "tyru",
            "is_restricted": false,
            "is_ultra_restricted": false
        },
        "blocks": [
            {
                "type": "rich_text",
                "block_id": "qds4",
                "elements": [
                    {
                        "type": "rich_text_section",
                        "elements": [
                            {
                                "type": "text",
                                "text": "buftype=acwrite 以外で buftype 設定されてたら弾くとかでもいい気がする"
                            }
                        ]
                    }
                ]
            }
        ]
    },
    {
        "client_msg_id": "c28b9bfb-273e-43e8-8e43-a095802e1430",
        "type": "message",
        "text": "式で判定できるように、とか。場合によっては遅延 (timer で) してから判定までできないとキビしいかもしれない",
        "user": "U03C71D7H",
        "ts": "1584254132.199700",
        "team": "T03C4RC8V",
        "user_team": "T03C4RC8V",
        "source_team": "T03C4RC8V",
        "user_profile": {
            "avatar_hash": "04a676b32692",
            "image_72": "https:\/\/avatars.slack-edge.com\/2015-01-15\/3417067010_04a676b32692fb2507e1_72.jpg",
            "first_name": "thinca",
            "real_name": "thinca",
            "display_name": "thinca",
            "team": "T03C4RC8V",
            "name": "thinca",
            "is_restricted": false,
            "is_ultra_restricted": false
        },
        "blocks": [
            {
                "type": "rich_text",
                "block_id": "H53G",
                "elements": [
                    {
                        "type": "rich_text_section",
                        "elements": [
                            {
                                "type": "text",
                                "text": "式で判定できるように、とか。場合によっては遅延 (timer で) してから判定までできないとキビしいかもしれない"
                            }
                        ]
                    }
                ]
            }
        ]
    },
    {
        "client_msg_id": "af715c81-304b-4e1c-b367-ad00ea10f2bc",
        "type": "message",
        "text": "qfreplace は acwrite",
        "user": "U03C71D7H",
        "ts": "1584254142.199900",
        "team": "T03C4RC8V",
        "user_team": "T03C4RC8V",
        "source_team": "T03C4RC8V",
        "user_profile": {
            "avatar_hash": "04a676b32692",
            "image_72": "https:\/\/avatars.slack-edge.com\/2015-01-15\/3417067010_04a676b32692fb2507e1_72.jpg",
            "first_name": "thinca",
            "real_name": "thinca",
            "display_name": "thinca",
            "team": "T03C4RC8V",
            "name": "thinca",
            "is_restricted": false,
            "is_ultra_restricted": false
        },
        "blocks": [
            {
                "type": "rich_text",
                "block_id": "A\/7N",
                "elements": [
                    {
                        "type": "rich_text_section",
                        "elements": [
                            {
                                "type": "text",
                                "text": "qfreplace は acwrite"
                            }
                        ]
                    }
                ]
            }
        ]
    },
    {
        "client_msg_id": "93a88062-b7ce-4f86-bc3b-531ea1b07d87",
        "type": "message",
        "text": "timer絡むとつらい",
        "user": "U9S4G0LJW",
        "ts": "1584254150.200300",
        "team": "T03C4RC8V",
        "user_team": "T03C4RC8V",
        "source_team": "T03C4RC8V",
        "user_profile": {
            "avatar_hash": "b6fceab653cf",
            "image_72": "https:\/\/avatars.slack-edge.com\/2018-03-19\/331496519296_b6fceab653cf61d7dd8b_72.png",
            "first_name": "kuu",
            "real_name": "kuu",
            "display_name": "kuu",
            "team": "T03C4RC8V",
            "name": "kuu",
            "is_restricted": false,
            "is_ultra_restricted": false
        },
        "blocks": [
            {
                "type": "rich_text",
                "block_id": "6jP8",
                "elements": [
                    {
                        "type": "rich_text_section",
                        "elements": [
                            {
                                "type": "text",
                                "text": "timer絡むとつらい"
                            }
                        ]
                    }
                ]
            }
        ]
    },
    {
        "client_msg_id": "646daa3b-d28f-4469-823b-538fef6ed65f",
        "type": "message",
        "text": "バッファが生成された瞬間って各種オプションがまだ設定されていなかったりする。たいてい、バッファを開いてからオプションをあれこれ設定するので",
        "user": "U03C71D7H",
        "ts": "1584254193.202000",
        "team": "T03C4RC8V",
        "user_team": "T03C4RC8V",
        "source_team": "T03C4RC8V",
        "user_profile": {
            "avatar_hash": "04a676b32692",
            "image_72": "https:\/\/avatars.slack-edge.com\/2015-01-15\/3417067010_04a676b32692fb2507e1_72.jpg",
            "first_name": "thinca",
            "real_name": "thinca",
            "display_name": "thinca",
            "team": "T03C4RC8V",
            "name": "thinca",
            "is_restricted": false,
            "is_ultra_restricted": false
        },
        "blocks": [
            {
                "type": "rich_text",
                "block_id": "E2JU",
                "elements": [
                    {
                        "type": "rich_text_section",
                        "elements": [
                            {
                                "type": "text",
                                "text": "バッファが生成された瞬間って各種オプションがまだ設定されていなかったりする。たいてい、バッファを開いてからオプションをあれこれ設定するので"
                            }
                        ]
                    }
                ]
            }
        ]
    },
    {
        "client_msg_id": "1067078e-9425-4664-ab8a-0b6205b789a2",
        "type": "message",
        "text": "これでもvim-lspは素直でしっかり設定できるんですよね\n全タイプとして '*' 、それのblacklistを設定できる\naleやcocは特定のタイプに紐付けが必要で anyとか any with excludeができない...",
        "user": "UAZ33BKV2",
        "ts": "1584254196.202300",
        "team": "T03C4RC8V",
        "user_team": "T03C4RC8V",
        "source_team": "T03C4RC8V",
        "user_profile": {
            "avatar_hash": "ed16847a152d",
            "image_72": "https:\/\/avatars.slack-edge.com\/2018-05-31\/373472791093_ed16847a152da533e013_72.png",
            "first_name": "",
            "real_name": "Tsuyoshi CHO",
            "display_name": "tsuyoshi_cho",
            "team": "T03C4RC8V",
            "name": "tsuyoshi_cho",
            "is_restricted": false,
            "is_ultra_restricted": false
        },
        "blocks": [
            {
                "type": "rich_text",
                "block_id": "bXu",
                "elements": [
                    {
                        "type": "rich_text_section",
                        "elements": [
                            {
                                "type": "text",
                                "text": "これでもvim-lspは素直でしっかり設定できるんですよね\n全タイプとして '*' 、それのblacklistを設定できる\naleやcocは特定のタイプに紐付けが必要で anyとか any with excludeができない..."
                            }
                        ]
                    }
                ]
            }
        ]
    },
    {
        "client_msg_id": "4eed4480-7611-4d89-8657-ec7d51237e56",
        "type": "message",
        "text": "buftype 見た感じ acwrite はなんか vim-lsp 走ってほしそうなケースもありそうな…\nbuftype が空かどうかで判断しちゃっていいのかな\\",
        "user": "U0M7GCBPD",
        "ts": "1584254212.203000",
        "team": "T03C4RC8V",
        "user_team": "T03C4RC8V",
        "source_team": "T03C4RC8V",
        "user_profile": {
            "avatar_hash": "gfdf83c448b8",
            "image_72": "https:\/\/secure.gravatar.com\/avatar\/5fdf83c448b8503add52517c7de0e3cc.jpg?s=72&d=https%3A%2F%2Fa.slack-edge.com%2Fdf10d%2Fimg%2Favatars%2Fava_0026-72.png",
            "first_name": "",
            "real_name": "tyru",
            "display_name": "",
            "team": "T03C4RC8V",
            "name": "tyru",
            "is_restricted": false,
            "is_ultra_restricted": false
        },
        "blocks": [
            {
                "type": "rich_text",
                "block_id": "KPk",
                "elements": [
                    {
                        "type": "rich_text_section",
                        "elements": [
                            {
                                "type": "text",
                                "text": "buftype 見た感じ acwrite はなんか vim-lsp 走ってほしそうなケースもありそうな…\nbuftype が空かどうかで判断しちゃっていいのかな\\"
                            }
                        ]
                    }
                ]
            }
        ]
    },
    {
        "client_msg_id": "fc5d4dc3-e681-4a7a-b1f1-d0c4ac9a58bf",
        "type": "message",
        "text": "Filetypeイベントで大体は平気なんですけどね...",
        "user": "UAZ33BKV2",
        "ts": "1584254226.203700",
        "team": "T03C4RC8V",
        "user_team": "T03C4RC8V",
        "source_team": "T03C4RC8V",
        "user_profile": {
            "avatar_hash": "ed16847a152d",
            "image_72": "https:\/\/avatars.slack-edge.com\/2018-05-31\/373472791093_ed16847a152da533e013_72.png",
            "first_name": "",
            "real_name": "Tsuyoshi CHO",
            "display_name": "tsuyoshi_cho",
            "team": "T03C4RC8V",
            "name": "tsuyoshi_cho",
            "is_restricted": false,
            "is_ultra_restricted": false
        },
        "blocks": [
            {
                "type": "rich_text",
                "block_id": "mU0",
                "elements": [
                    {
                        "type": "rich_text_section",
                        "elements": [
                            {
                                "type": "text",
                                "text": "Filetypeイベントで大体は平気なんですけどね..."
                            }
                        ]
                    }
                ]
            }
        ]
    },
    {
        "client_msg_id": "87fe181a-2056-4063-823a-909941c89f95",
        "type": "message",
        "text": "そもそも filetype だけで判断するのに無理がある…",
        "user": "U03C71D7H",
        "ts": "1584254230.203800",
        "team": "T03C4RC8V",
        "user_team": "T03C4RC8V",
        "source_team": "T03C4RC8V",
        "user_profile": {
            "avatar_hash": "04a676b32692",
            "image_72": "https:\/\/avatars.slack-edge.com\/2015-01-15\/3417067010_04a676b32692fb2507e1_72.jpg",
            "first_name": "thinca",
            "real_name": "thinca",
            "display_name": "thinca",
            "team": "T03C4RC8V",
            "name": "thinca",
            "is_restricted": false,
            "is_ultra_restricted": false
        },
        "blocks": [
            {
                "type": "rich_text",
                "block_id": "Gmb",
                "elements": [
                    {
                        "type": "rich_text_section",
                        "elements": [
                            {
                                "type": "text",
                                "text": "そもそも filetype だけで判断するのに無理がある…"
                            }
                        ]
                    }
                ]
            }
        ]
    },
    {
        "client_msg_id": "0b43f44f-a550-46dd-a425-6e417bb62cdf",
        "type": "message",
        "text": "acwriteってnetrwとかmetarwとか走った時になるやつか、だとしたらありそう",
        "user": "U9S4G0LJW",
        "ts": "1584254285.204800",
        "team": "T03C4RC8V",
        "user_team": "T03C4RC8V",
        "source_team": "T03C4RC8V",
        "user_profile": {
            "avatar_hash": "b6fceab653cf",
            "image_72": "https:\/\/avatars.slack-edge.com\/2018-03-19\/331496519296_b6fceab653cf61d7dd8b_72.png",
            "first_name": "kuu",
            "real_name": "kuu",
            "display_name": "kuu",
            "team": "T03C4RC8V",
            "name": "kuu",
            "is_restricted": false,
            "is_ultra_restricted": false
        },
        "blocks": [
            {
                "type": "rich_text",
                "block_id": "NDn+h",
                "elements": [
                    {
                        "type": "rich_text_section",
                        "elements": [
                            {
                                "type": "text",
                                "text": "acwriteってnetrwとかmetarwとか走った時になるやつか、だとしたらありそう"
                            }
                        ]
                    }
                ]
            }
        ]
    },
    {
        "client_msg_id": "30832d37-28f2-42bf-8e28-627b58d100f3",
        "type": "message",
        "text": "いやーあれか。個人向けの設定ならそれでもまあだいたいなんとかなるけど、汎用的な設定を作ろうとしているのがしんどいのかなー",
        "user": "U03C71D7H",
        "ts": "1584254291.205000",
        "team": "T03C4RC8V",
        "user_team": "T03C4RC8V",
        "source_team": "T03C4RC8V",
        "user_profile": {
            "avatar_hash": "04a676b32692",
            "image_72": "https:\/\/avatars.slack-edge.com\/2015-01-15\/3417067010_04a676b32692fb2507e1_72.jpg",
            "first_name": "thinca",
            "real_name": "thinca",
            "display_name": "thinca",
            "team": "T03C4RC8V",
            "name": "thinca",
            "is_restricted": false,
            "is_ultra_restricted": false
        },
        "blocks": [
            {
                "type": "rich_text",
                "block_id": "zPcb",
                "elements": [
                    {
                        "type": "rich_text_section",
                        "elements": [
                            {
                                "type": "text",
                                "text": "いやーあれか。個人向けの設定ならそれでもまあだいたいなんとかなるけど、汎用的な設定を作ろうとしているのがしんどいのかなー"
                            }
                        ]
                    }
                ]
            }
        ]
    },
    {
        "client_msg_id": "d996a95f-1ca8-4df9-a3ef-ab432a2de609",
        "type": "message",
        "text": "個人だと10個くらい調べて弾けばどうにかなりますしねぇ",
        "user": "U8996GYBF",
        "ts": "1584254367.205300",
        "team": "T03C4RC8V",
        "user_team": "T03C4RC8V",
        "source_team": "T03C4RC8V",
        "user_profile": {
            "avatar_hash": "48b1c10b3cf4",
            "image_72": "https:\/\/avatars.slack-edge.com\/2018-03-09\/327298108645_48b1c10b3cf4092337c5_72.png",
            "first_name": "ycino",
            "real_name": "ycino",
            "display_name": "ycino",
            "team": "T03C4RC8V",
            "name": "yuki.ycino",
            "is_restricted": false,
            "is_ultra_restricted": false
        },
        "blocks": [
            {
                "type": "rich_text",
                "block_id": "9g3G",
                "elements": [
                    {
                        "type": "rich_text_section",
                        "elements": [
                            {
                                "type": "text",
                                "text": "個人だと10個くらい調べて弾けばどうにかなりますしねぇ"
                            }
                        ]
                    }
                ]
            }
        ]
    },
    {
        "client_msg_id": "d64e207b-ec78-4d67-99c0-ab8a44629a32",
        "type": "message",
        "text": "まー、できるだけ、なので辛くなったら止めますw",
        "user": "UAZ33BKV2",
        "ts": "1584254714.205700",
        "team": "T03C4RC8V",
        "user_team": "T03C4RC8V",
        "source_team": "T03C4RC8V",
        "user_profile": {
            "avatar_hash": "ed16847a152d",
            "image_72": "https:\/\/avatars.slack-edge.com\/2018-05-31\/373472791093_ed16847a152da533e013_72.png",
            "first_name": "",
            "real_name": "Tsuyoshi CHO",
            "display_name": "tsuyoshi_cho",
            "team": "T03C4RC8V",
            "name": "tsuyoshi_cho",
            "is_restricted": false,
            "is_ultra_restricted": false
        },
        "blocks": [
            {
                "type": "rich_text",
                "block_id": "vgQ8",
                "elements": [
                    {
                        "type": "rich_text_section",
                        "elements": [
                            {
                                "type": "text",
                                "text": "まー、できるだけ、なので辛くなったら止めますw"
                            }
                        ]
                    }
                ]
            }
        ]
    },
    {
        "client_msg_id": "a52560b8-9671-4627-a1e4-600a85cb8a57",
        "type": "message",
        "text": "あと、設定は可能なので、自分で追加(ただし効くのはvim-lsp)で",
        "user": "UAZ33BKV2",
        "ts": "1584254742.206200",
        "team": "T03C4RC8V",
        "user_team": "T03C4RC8V",
        "source_team": "T03C4RC8V",
        "user_profile": {
            "avatar_hash": "ed16847a152d",
            "image_72": "https:\/\/avatars.slack-edge.com\/2018-05-31\/373472791093_ed16847a152da533e013_72.png",
            "first_name": "",
            "real_name": "Tsuyoshi CHO",
            "display_name": "tsuyoshi_cho",
            "team": "T03C4RC8V",
            "name": "tsuyoshi_cho",
            "is_restricted": false,
            "is_ultra_restricted": false
        },
        "blocks": [
            {
                "type": "rich_text",
                "block_id": "54OpN",
                "elements": [
                    {
                        "type": "rich_text_section",
                        "elements": [
                            {
                                "type": "text",
                                "text": "あと、設定は可能なので、自分で追加(ただし効くのはvim-lsp)で"
                            }
                        ]
                    }
                ]
            }
        ]
    },
    {
        "client_msg_id": "854d3bab-571f-4b00-9bdd-cc5989e8f60b",
        "type": "message",
        "text": "PRs are welcome というスタンスで良さそうですねw",
        "user": "U78A6ESHM",
        "ts": "1584254987.206800",
        "team": "T03C4RC8V",
        "user_team": "T03C4RC8V",
        "source_team": "T03C4RC8V",
        "user_profile": {
            "avatar_hash": "aa245483338d",
            "image_72": "https:\/\/avatars.slack-edge.com\/2019-11-14\/833953864853_aa245483338df08cd3b2_72.png",
            "first_name": "heavenshell",
            "real_name": "heavenshell",
            "display_name": "heavenshell",
            "team": "T03C4RC8V",
            "name": "heavenshell",
            "is_restricted": false,
            "is_ultra_restricted": false
        },
        "blocks": [
            {
                "type": "rich_text",
                "block_id": "TV6KX",
                "elements": [
                    {
                        "type": "rich_text_section",
                        "elements": [
                            {
                                "type": "text",
                                "text": "PRs are welcome というスタンスで良さそうですねw"
                            }
                        ]
                    }
                ]
            }
        ],
        "reactions": [
            {
                "name": "sorena",
                "users": [
                    "UAZ33BKV2"
                ],
                "count": 1
            }
        ]
    }
]